<?xml version="1.0"?>   
<params>   
  <defaults>   
  <normal   
    sanitycheck="0"
    min_window_radius="1" 
    max_window_radius="10" 
    nwindow_radii="3" 
    window_offsets="0,-1,1" 
    trans_types="none"  >
    <mean min_window_radius="0"/>
    <min/>
    <max/>
    <change change_window_radii="1,3"/>
    <std/>
    <harmonic num_harmonic="3"/>
    <diff_neighbor_mean/>
    <diff_neighbor_min/>
    <diff_neighbor_max/>
    <zscore_neighbors/>
  </normal>
  
  <more
    sanitycheck="0"
    min_window_radius="1" 
    max_window_radius="10" 
    nwindow_radii="5" 
    window_offsets="0,0.5,-0.5,-1,1" 
    trans_types="none"  >
    <mean min_window_radius="0"/>
    <min/>
    <max/>
    <hist hist_edges="-1,1"/>
    <change change_window_radii="1,3"/>
    <std/>
    <harmonic num_harmonic="5"/>
    <diff_neighbor_mean/>
    <diff_neighbor_min/>
    <diff_neighbor_max/>
    <zscore_neighbors/>
  </more>  
  
  <less
    sanitycheck="0"
    min_window_radius="1" 
    max_window_radius="10" 
    nwindow_radii="2" 
    window_offsets="0,-1,1" 
    trans_types="none"  >
    <mean min_window_radius="0"/>
    <min/>
    <max/>
    <change change_window_radii="1,3"/>
    <std/>
    <harmonic num_harmonic="3"/>
    <diff_neighbor_mean/>
    <diff_neighbor_min/>
    <diff_neighbor_max/>
    <zscore_neighbors/>
  </less>

  <hoghof   
    sanitycheck="0"   
    min_window_radius="5"    
    max_window_radius="10"    
    nwindow_radii="3"    
    window_offsets="0,-1,1"    
    trans_types="none"  >   
    <mean min_window_radius="5"/>   
  </hoghof>   
     
  </defaults>   
     
  <perframe>   
    <a_mm trans_types="none,abs" type="appearance"/>
    
    <absanglefrom1to2_nose2ell  trans_types="none" type="social"/>

    <absdtheta trans_types="relative" type="locomotion"/>
    
    <absdv_cor trans_types="relative" type="locomotion"/>
    
    <absphidiff_anglesub trans_types="none" type="social"/>
    
    <absphidiff_nose2ell trans_types="none" type="social"/>
    
    <absthetadiff_anglesub trans_types="none" type="social"/>
    
    <absthetadiff_nose2ell trans_types="none" type="social"/>
    
    <angle2wall trans_types="flip,abs" type="arena"/>
    
    <anglefrom1to2_anglesub trans_types="flip,abs" type="social"/>
    
    <anglefrom1to2_nose2ell  trans_types="flip,abs" type="social"/>
    
    <angleonclosestfly trans_types="flip,abs" type="social"/>
    
    <anglesub trans_types="none" type="social"/>
    
    <area trans_types="none,relative" type="appearance"/>
    
    <arena_angle trans_types="none" type="position"/>
    
    <arena_r trans_types="none" type="arena,position"/>
    
    <b_mm trans_types="none,abs" type="appearance"/>
    
    <closestfly_anglesub trans_types="none" type="identity"/>
    
    <closestfly_center  trans_types="none" type="identity"/>
    
    <closestfly_ell2nose  trans_types="none" type="identity"/>
    
    <closestfly_nose2ell  trans_types="none" type="identity"/>
    
    <corfrac_maj trans_types="none,abs" type="locomotion"/>
    
    <corfrac_min trans_types="flip,abs" type="locomotion"/>
    
    <dangle2wall trans_types="flip,abs" type="arena"/>
    
    <danglesub trans_types="none,abs" type="social"/>
    
    <darea trans_types="none,abs,relative" type="appearance"/>
    
    <da trans_types="none,abs,relative" type="appearance"/>
    
    <db trans_types="none,abs,relative" type="appearance"/>

    <dcenter trans_types="none,relative" type="social"/>
    
    <ddcenter trans_types="none,abs" type="social"/>
    
    <ddist2wall trans_types="none" type="arena"/>
    
    <decc trans_types="none,abs,relative" type="appearance"/>
    
    <dell2nose trans_types="none,relative" type="social"/>
    
    <dnose2ell_angle_30tomin30 trans_types="none" type="social"/>
    
    <dnose2ell_angle_min20to20 trans_types="none" type="social"/>
    
    <dnose2ell_angle_min30to30 trans_types="none" type="social"/>
    
    <dist2wall trans_types="none,relative" type="arena"/>
    
    <dnose2ell trans_types="none,relative" type="social"/>
    
    <dnose2tail trans_types="none,relative" type="social"/>
    
    <dphi trans_types="none,abs" type="locomotion"/>
    
    <dtheta trans_types="flip,abs" type="locomotion"/>
    
    <du_cor trans_types="none,abs,relative" type="locomotion"/>
    
    <du_ctr trans_types="none,abs,relative" type="locomotion"/>
    
    <du_tail trans_types="none,abs,relative" type="locomotion"/>
    
    <dv_cor trans_types="flip,abs" type="locomotion"/>
    
    <dv_ctr trans_types="flip,abs" type="locomotion"/>
    
    <dv_tail trans_types="flip,abs" type="locomotion"/>
    
    <ecc trans_types="none,abs" type="appearance"/>
    
    <flipdv_cor trans_types="relative" type="locomotion"/>
    
    <magveldiff_anglesub trans_types="none,relative" type="social"/>
    
    <magveldiff_nose2ell trans_types="none,relative" type="social"/>
    
    <nflies_close trans_types="none" type="social"/>

    <phi trans_types="none" type="position"/>
    
    <phisideways trans_types="none" type="locomotion"/>
    
    <velmag trans_types="none,relative" type="locomotion"/>
    
    <velmag_ctr trans_types="none,relative" type="locomotion"/>
    
    <velmag_nose trans_types="none,relative" type="locomotion"/>
    
    <velmag_tail trans_types="none,relative" type="locomotion"/>
    
    <veltoward_anglesub trans_types="none,relative" type="social"/>
    
    <veltoward_nose2ell trans_types="none,relative" type="social"/>
    
    <yaw trans_types="flip,abs" type="locomotion"/>
    
    <absyaw trans_types="none" type="compatbility"/>

    <hogftrs_0001 trans_types="none" type="hog"/>  
    <hogftrs_0002 trans_types="none" type="hog"/>  
    <hogftrs_0003 trans_types="none" type="hog"/>  
    <hogftrs_0004 trans_types="none" type="hog"/>  
    <hogftrs_0005 trans_types="none" type="hog"/>  
    <hogftrs_0006 trans_types="none" type="hog"/>  
    <hogftrs_0007 trans_types="none" type="hog"/>  
    <hogftrs_0008 trans_types="none" type="hog"/>  
    <hogftrs_0009 trans_types="none" type="hog"/>  
    <hogftrs_0010 trans_types="none" type="hog"/>  
    <hogftrs_0011 trans_types="none" type="hog"/>  
    <hogftrs_0012 trans_types="none" type="hog"/>  
    <hogftrs_0013 trans_types="none" type="hog"/>  
    <hogftrs_0014 trans_types="none" type="hog"/>  
    <hogftrs_0015 trans_types="none" type="hog"/>  
    <hogftrs_0016 trans_types="none" type="hog"/>  
    <hogftrs_0017 trans_types="none" type="hog"/>  
    <hogftrs_0018 trans_types="none" type="hog"/>  
    <hogftrs_0019 trans_types="none" type="hog"/>  
    <hogftrs_0020 trans_types="none" type="hog"/>  
    <hogftrs_0021 trans_types="none" type="hog"/>  
    <hogftrs_0022 trans_types="none" type="hog"/>  
    <hogftrs_0023 trans_types="none" type="hog"/>  
    <hogftrs_0024 trans_types="none" type="hog"/>  
    <hogftrs_0025 trans_types="none" type="hog"/>  
    <hogftrs_0026 trans_types="none" type="hog"/>  
    <hogftrs_0027 trans_types="none" type="hog"/>  
    <hogftrs_0028 trans_types="none" type="hog"/>  
    <hogftrs_0029 trans_types="none" type="hog"/>  
    <hogftrs_0030 trans_types="none" type="hog"/>  
    <hogftrs_0031 trans_types="none" type="hog"/>  
    <hogftrs_0032 trans_types="none" type="hog"/>  
    <hogftrs_0033 trans_types="none" type="hog"/>  
    <hogftrs_0034 trans_types="none" type="hog"/>  
    <hogftrs_0035 trans_types="none" type="hog"/>  
    <hogftrs_0036 trans_types="none" type="hog"/>  
    <hogftrs_0037 trans_types="none" type="hog"/>  
    <hogftrs_0038 trans_types="none" type="hog"/>  
    <hogftrs_0039 trans_types="none" type="hog"/>  
    <hogftrs_0040 trans_types="none" type="hog"/>  
    <hogftrs_0041 trans_types="none" type="hog"/>  
    <hogftrs_0042 trans_types="none" type="hog"/>  
    <hogftrs_0043 trans_types="none" type="hog"/>  
    <hogftrs_0044 trans_types="none" type="hog"/>  
    <hogftrs_0045 trans_types="none" type="hog"/>  
    <hogftrs_0046 trans_types="none" type="hog"/>  
    <hogftrs_0047 trans_types="none" type="hog"/>  
    <hogftrs_0048 trans_types="none" type="hog"/>  
    <hogftrs_0049 trans_types="none" type="hog"/>  
    <hogftrs_0050 trans_types="none" type="hog"/>  
    <hogftrs_0051 trans_types="none" type="hog"/>  
    <hogftrs_0052 trans_types="none" type="hog"/>  
    <hogftrs_0053 trans_types="none" type="hog"/>  
    <hogftrs_0054 trans_types="none" type="hog"/>  
    <hogftrs_0055 trans_types="none" type="hog"/>  
    <hogftrs_0056 trans_types="none" type="hog"/>  
    <hogftrs_0057 trans_types="none" type="hog"/>  
    <hogftrs_0058 trans_types="none" type="hog"/>  
    <hogftrs_0059 trans_types="none" type="hog"/>  
    <hogftrs_0060 trans_types="none" type="hog"/>  
    <hogftrs_0061 trans_types="none" type="hog"/>  
    <hogftrs_0062 trans_types="none" type="hog"/>  
    <hogftrs_0063 trans_types="none" type="hog"/>  
    <hogftrs_0064 trans_types="none" type="hog"/>  
    <hogftrs_0065 trans_types="none" type="hog"/>  
    <hogftrs_0066 trans_types="none" type="hog"/>  
    <hogftrs_0067 trans_types="none" type="hog"/>  
    <hogftrs_0068 trans_types="none" type="hog"/>  
    <hogftrs_0069 trans_types="none" type="hog"/>  
    <hogftrs_0070 trans_types="none" type="hog"/>  
    <hogftrs_0071 trans_types="none" type="hog"/>  
    <hogftrs_0072 trans_types="none" type="hog"/>  
    <hogftrs_0073 trans_types="none" type="hog"/>  
    <hogftrs_0074 trans_types="none" type="hog"/>  
    <hogftrs_0075 trans_types="none" type="hog"/>  
    <hogftrs_0076 trans_types="none" type="hog"/>  
    <hogftrs_0077 trans_types="none" type="hog"/>  
    <hogftrs_0078 trans_types="none" type="hog"/>  
    <hogftrs_0079 trans_types="none" type="hog"/>  
    <hogftrs_0080 trans_types="none" type="hog"/>  
    <hogftrs_0081 trans_types="none" type="hog"/>  
    <hogftrs_0082 trans_types="none" type="hog"/>  
    <hogftrs_0083 trans_types="none" type="hog"/>  
    <hogftrs_0084 trans_types="none" type="hog"/>  
    <hogftrs_0085 trans_types="none" type="hog"/>  
    <hogftrs_0086 trans_types="none" type="hog"/>  
    <hogftrs_0087 trans_types="none" type="hog"/>  
    <hogftrs_0088 trans_types="none" type="hog"/>  
    <hogftrs_0089 trans_types="none" type="hog"/>  
    <hogftrs_0090 trans_types="none" type="hog"/>  
    <hogftrs_0091 trans_types="none" type="hog"/>  
    <hogftrs_0092 trans_types="none" type="hog"/>  
    <hogftrs_0093 trans_types="none" type="hog"/>  
    <hogftrs_0094 trans_types="none" type="hog"/>  
    <hogftrs_0095 trans_types="none" type="hog"/>  
    <hogftrs_0096 trans_types="none" type="hog"/>  
    <hogftrs_0097 trans_types="none" type="hog"/>  
    <hogftrs_0098 trans_types="none" type="hog"/>  
    <hogftrs_0099 trans_types="none" type="hog"/>  
    <hogftrs_0100 trans_types="none" type="hog"/>  
    <hogftrs_0101 trans_types="none" type="hog"/>  
    <hogftrs_0102 trans_types="none" type="hog"/>  
    <hogftrs_0103 trans_types="none" type="hog"/>  
    <hogftrs_0104 trans_types="none" type="hog"/>  
    <hogftrs_0105 trans_types="none" type="hog"/>  
    <hogftrs_0106 trans_types="none" type="hog"/>  
    <hogftrs_0107 trans_types="none" type="hog"/>  
    <hogftrs_0108 trans_types="none" type="hog"/>  
    <hogftrs_0109 trans_types="none" type="hog"/>  
    <hogftrs_0110 trans_types="none" type="hog"/>  
    <hogftrs_0111 trans_types="none" type="hog"/>  
    <hogftrs_0112 trans_types="none" type="hog"/>  
    <hogftrs_0113 trans_types="none" type="hog"/>  
    <hogftrs_0114 trans_types="none" type="hog"/>  
    <hogftrs_0115 trans_types="none" type="hog"/>  
    <hogftrs_0116 trans_types="none" type="hog"/>  
    <hogftrs_0117 trans_types="none" type="hog"/>  
    <hogftrs_0118 trans_types="none" type="hog"/>  
    <hogftrs_0119 trans_types="none" type="hog"/>  
    <hogftrs_0120 trans_types="none" type="hog"/>  
    <hogftrs_0121 trans_types="none" type="hog"/>  
    <hogftrs_0122 trans_types="none" type="hog"/>  
    <hogftrs_0123 trans_types="none" type="hog"/>  
    <hogftrs_0124 trans_types="none" type="hog"/>  
    <hogftrs_0125 trans_types="none" type="hog"/>  
    <hogftrs_0126 trans_types="none" type="hog"/>  
    <hogftrs_0127 trans_types="none" type="hog"/>  
    <hogftrs_0128 trans_types="none" type="hog"/>  
    <hogftrs_0129 trans_types="none" type="hog"/>  
    <hogftrs_0130 trans_types="none" type="hog"/>  
    <hogftrs_0131 trans_types="none" type="hog"/>  
    <hogftrs_0132 trans_types="none" type="hog"/>  
    <hogftrs_0133 trans_types="none" type="hog"/>  
    <hogftrs_0134 trans_types="none" type="hog"/>  
    <hogftrs_0135 trans_types="none" type="hog"/>  
    <hogftrs_0136 trans_types="none" type="hog"/>  
    <hogftrs_0137 trans_types="none" type="hog"/>  
    <hogftrs_0138 trans_types="none" type="hog"/>  
    <hogftrs_0139 trans_types="none" type="hog"/>  
    <hogftrs_0140 trans_types="none" type="hog"/>  
    <hogftrs_0141 trans_types="none" type="hog"/>  
    <hogftrs_0142 trans_types="none" type="hog"/>  
    <hogftrs_0143 trans_types="none" type="hog"/>  
    <hogftrs_0144 trans_types="none" type="hog"/>  
    <hogftrs_0145 trans_types="none" type="hog"/>  
    <hogftrs_0146 trans_types="none" type="hog"/>  
    <hogftrs_0147 trans_types="none" type="hog"/>  
    <hogftrs_0148 trans_types="none" type="hog"/>  
    <hogftrs_0149 trans_types="none" type="hog"/>  
    <hogftrs_0150 trans_types="none" type="hog"/>  
    <hogftrs_0151 trans_types="none" type="hog"/>  
    <hogftrs_0152 trans_types="none" type="hog"/>  
    <hogftrs_0153 trans_types="none" type="hog"/>  
    <hogftrs_0154 trans_types="none" type="hog"/>  
    <hogftrs_0155 trans_types="none" type="hog"/>  
    <hogftrs_0156 trans_types="none" type="hog"/>  
    <hogftrs_0157 trans_types="none" type="hog"/>  
    <hogftrs_0158 trans_types="none" type="hog"/>  
    <hogftrs_0159 trans_types="none" type="hog"/>  
    <hogftrs_0160 trans_types="none" type="hog"/>  
    <hogftrs_0161 trans_types="none" type="hog"/>  
    <hogftrs_0162 trans_types="none" type="hog"/>  
    <hogftrs_0163 trans_types="none" type="hog"/>  
    <hogftrs_0164 trans_types="none" type="hog"/>  
    <hogftrs_0165 trans_types="none" type="hog"/>  
    <hogftrs_0166 trans_types="none" type="hog"/>  
    <hogftrs_0167 trans_types="none" type="hog"/>  
    <hogftrs_0168 trans_types="none" type="hog"/>  
    <hogftrs_0169 trans_types="none" type="hog"/>  
    <hogftrs_0170 trans_types="none" type="hog"/>  
    <hogftrs_0171 trans_types="none" type="hog"/>  
    <hogftrs_0172 trans_types="none" type="hog"/>  
    <hogftrs_0173 trans_types="none" type="hog"/>  
    <hogftrs_0174 trans_types="none" type="hog"/>  
    <hogftrs_0175 trans_types="none" type="hog"/>  
    <hogftrs_0176 trans_types="none" type="hog"/>  
    <hogftrs_0177 trans_types="none" type="hog"/>  
    <hogftrs_0178 trans_types="none" type="hog"/>  
    <hogftrs_0179 trans_types="none" type="hog"/>  
    <hogftrs_0180 trans_types="none" type="hog"/>  
    <hogftrs_0181 trans_types="none" type="hog"/>  
    <hogftrs_0182 trans_types="none" type="hog"/>  
    <hogftrs_0183 trans_types="none" type="hog"/>  
    <hogftrs_0184 trans_types="none" type="hog"/>  
    <hogftrs_0185 trans_types="none" type="hog"/>  
    <hogftrs_0186 trans_types="none" type="hog"/>  
    <hogftrs_0187 trans_types="none" type="hog"/>  
    <hogftrs_0188 trans_types="none" type="hog"/>  
    <hogftrs_0189 trans_types="none" type="hog"/>  
    <hogftrs_0190 trans_types="none" type="hog"/>  
    <hogftrs_0191 trans_types="none" type="hog"/>  
    <hogftrs_0192 trans_types="none" type="hog"/>  
    <hogftrs_0193 trans_types="none" type="hog"/>  
    <hogftrs_0194 trans_types="none" type="hog"/>  
    <hogftrs_0195 trans_types="none" type="hog"/>  
    <hogftrs_0196 trans_types="none" type="hog"/>  
    <hogftrs_0197 trans_types="none" type="hog"/>  
    <hogftrs_0198 trans_types="none" type="hog"/>  
    <hogftrs_0199 trans_types="none" type="hog"/>  
    <hogftrs_0200 trans_types="none" type="hog"/>  
    <hogftrs_0201 trans_types="none" type="hog"/>  
    <hogftrs_0202 trans_types="none" type="hog"/>  
    <hogftrs_0203 trans_types="none" type="hog"/>  
    <hogftrs_0204 trans_types="none" type="hog"/>  
    <hogftrs_0205 trans_types="none" type="hog"/>  
    <hogftrs_0206 trans_types="none" type="hog"/>  
    <hogftrs_0207 trans_types="none" type="hog"/>  
    <hogftrs_0208 trans_types="none" type="hog"/>  
    <hogftrs_0209 trans_types="none" type="hog"/>  
    <hogftrs_0210 trans_types="none" type="hog"/>  
    <hogftrs_0211 trans_types="none" type="hog"/>  
    <hogftrs_0212 trans_types="none" type="hog"/>  
    <hogftrs_0213 trans_types="none" type="hog"/>  
    <hogftrs_0214 trans_types="none" type="hog"/>  
    <hogftrs_0215 trans_types="none" type="hog"/>  
    <hogftrs_0216 trans_types="none" type="hog"/>  
    <hogftrs_0217 trans_types="none" type="hog"/>  
    <hogftrs_0218 trans_types="none" type="hog"/>  
    <hogftrs_0219 trans_types="none" type="hog"/>  
    <hogftrs_0220 trans_types="none" type="hog"/>  
    <hogftrs_0221 trans_types="none" type="hog"/>  
    <hogftrs_0222 trans_types="none" type="hog"/>  
    <hogftrs_0223 trans_types="none" type="hog"/>  
    <hogftrs_0224 trans_types="none" type="hog"/>  
    <hogftrs_0225 trans_types="none" type="hog"/>  
    <hogftrs_0226 trans_types="none" type="hog"/>  
    <hogftrs_0227 trans_types="none" type="hog"/>  
    <hogftrs_0228 trans_types="none" type="hog"/>  
    <hogftrs_0229 trans_types="none" type="hog"/>  
    <hogftrs_0230 trans_types="none" type="hog"/>  
    <hogftrs_0231 trans_types="none" type="hog"/>  
    <hogftrs_0232 trans_types="none" type="hog"/>  
    <hogftrs_0233 trans_types="none" type="hog"/>  
    <hogftrs_0234 trans_types="none" type="hog"/>  
    <hogftrs_0235 trans_types="none" type="hog"/>  
    <hogftrs_0236 trans_types="none" type="hog"/>  
    <hogftrs_0237 trans_types="none" type="hog"/>  
    <hogftrs_0238 trans_types="none" type="hog"/>  
    <hogftrs_0239 trans_types="none" type="hog"/>  
    <hogftrs_0240 trans_types="none" type="hog"/>  
    <hogftrs_0241 trans_types="none" type="hog"/>  
    <hogftrs_0242 trans_types="none" type="hog"/>  
    <hogftrs_0243 trans_types="none" type="hog"/>  
    <hogftrs_0244 trans_types="none" type="hog"/>  
    <hogftrs_0245 trans_types="none" type="hog"/>  
    <hogftrs_0246 trans_types="none" type="hog"/>  
    <hogftrs_0247 trans_types="none" type="hog"/>  
    <hogftrs_0248 trans_types="none" type="hog"/>  
    <hogftrs_0249 trans_types="none" type="hog"/>  
    <hogftrs_0250 trans_types="none" type="hog"/>  
    <hogftrs_0251 trans_types="none" type="hog"/>  
    <hogftrs_0252 trans_types="none" type="hog"/>  
    <hogftrs_0253 trans_types="none" type="hog"/>  
    <hogftrs_0254 trans_types="none" type="hog"/>  
    <hogftrs_0255 trans_types="none" type="hog"/>  
    <hogftrs_0256 trans_types="none" type="hog"/>  
    <hogftrs_0257 trans_types="none" type="hog"/>  
    <hogftrs_0258 trans_types="none" type="hog"/>  
    <hogftrs_0259 trans_types="none" type="hog"/>  
    <hogftrs_0260 trans_types="none" type="hog"/>  
    <hogftrs_0261 trans_types="none" type="hog"/>  
    <hogftrs_0262 trans_types="none" type="hog"/>  
    <hogftrs_0263 trans_types="none" type="hog"/>  
    <hogftrs_0264 trans_types="none" type="hog"/>  
    <hogftrs_0265 trans_types="none" type="hog"/>  
    <hogftrs_0266 trans_types="none" type="hog"/>  
    <hogftrs_0267 trans_types="none" type="hog"/>  
    <hogftrs_0268 trans_types="none" type="hog"/>  
    <hogftrs_0269 trans_types="none" type="hog"/>  
    <hogftrs_0270 trans_types="none" type="hog"/>  
    <hogftrs_0271 trans_types="none" type="hog"/>  
    <hogftrs_0272 trans_types="none" type="hog"/>  
    <hogftrs_0273 trans_types="none" type="hog"/>  
    <hogftrs_0274 trans_types="none" type="hog"/>  
    <hogftrs_0275 trans_types="none" type="hog"/>  
    <hogftrs_0276 trans_types="none" type="hog"/>  
    <hogftrs_0277 trans_types="none" type="hog"/>  
    <hogftrs_0278 trans_types="none" type="hog"/>  
    <hogftrs_0279 trans_types="none" type="hog"/>  
    <hogftrs_0280 trans_types="none" type="hog"/>  
    <hogftrs_0281 trans_types="none" type="hog"/>  
    <hogftrs_0282 trans_types="none" type="hog"/>  
    <hogftrs_0283 trans_types="none" type="hog"/>  
    <hogftrs_0284 trans_types="none" type="hog"/>  
    <hogftrs_0285 trans_types="none" type="hog"/>  
    <hogftrs_0286 trans_types="none" type="hog"/>  
    <hogftrs_0287 trans_types="none" type="hog"/>  
    <hogftrs_0288 trans_types="none" type="hog"/>  
    <hogftrs_0289 trans_types="none" type="hog"/>  
    <hogftrs_0290 trans_types="none" type="hog"/>  
    <hogftrs_0291 trans_types="none" type="hog"/>  
    <hogftrs_0292 trans_types="none" type="hog"/>  
    <hogftrs_0293 trans_types="none" type="hog"/>  
    <hogftrs_0294 trans_types="none" type="hog"/>  
    <hogftrs_0295 trans_types="none" type="hog"/>  
    <hogftrs_0296 trans_types="none" type="hog"/>  
    <hogftrs_0297 trans_types="none" type="hog"/>  
    <hogftrs_0298 trans_types="none" type="hog"/>  
    <hogftrs_0299 trans_types="none" type="hog"/>  
    <hogftrs_0300 trans_types="none" type="hog"/>  
    <hogftrs_0301 trans_types="none" type="hog"/>  
    <hogftrs_0302 trans_types="none" type="hog"/>  
    <hogftrs_0303 trans_types="none" type="hog"/>  
    <hogftrs_0304 trans_types="none" type="hog"/>  
    <hogftrs_0305 trans_types="none" type="hog"/>  
    <hogftrs_0306 trans_types="none" type="hog"/>  
    <hogftrs_0307 trans_types="none" type="hog"/>  
    <hogftrs_0308 trans_types="none" type="hog"/>  
    <hogftrs_0309 trans_types="none" type="hog"/>  
    <hogftrs_0310 trans_types="none" type="hog"/>  
    <hogftrs_0311 trans_types="none" type="hog"/>  
    <hogftrs_0312 trans_types="none" type="hog"/>  
    <hogftrs_0313 trans_types="none" type="hog"/>  
    <hogftrs_0314 trans_types="none" type="hog"/>  
    <hogftrs_0315 trans_types="none" type="hog"/>  
    <hogftrs_0316 trans_types="none" type="hog"/>  
    <hogftrs_0317 trans_types="none" type="hog"/>  
    <hogftrs_0318 trans_types="none" type="hog"/>  
    <hogftrs_0319 trans_types="none" type="hog"/>  
    <hogftrs_0320 trans_types="none" type="hog"/>  
    <hogftrs_0321 trans_types="none" type="hog"/>  
    <hogftrs_0322 trans_types="none" type="hog"/>  
    <hogftrs_0323 trans_types="none" type="hog"/>  
    <hogftrs_0324 trans_types="none" type="hog"/>  
    <hogftrs_0325 trans_types="none" type="hog"/>  
    <hogftrs_0326 trans_types="none" type="hog"/>  
    <hogftrs_0327 trans_types="none" type="hog"/>  
    <hogftrs_0328 trans_types="none" type="hog"/>  
    <hogftrs_0329 trans_types="none" type="hog"/>  
    <hogftrs_0330 trans_types="none" type="hog"/>  
    <hogftrs_0331 trans_types="none" type="hog"/>  
    <hogftrs_0332 trans_types="none" type="hog"/>  
    <hogftrs_0333 trans_types="none" type="hog"/>  
    <hogftrs_0334 trans_types="none" type="hog"/>  
    <hogftrs_0335 trans_types="none" type="hog"/>  
    <hogftrs_0336 trans_types="none" type="hog"/>  
    <hogftrs_0337 trans_types="none" type="hog"/>  
    <hogftrs_0338 trans_types="none" type="hog"/>  
    <hogftrs_0339 trans_types="none" type="hog"/>  
    <hogftrs_0340 trans_types="none" type="hog"/>  
    <hogftrs_0341 trans_types="none" type="hog"/>  
    <hogftrs_0342 trans_types="none" type="hog"/>  
    <hogftrs_0343 trans_types="none" type="hog"/>  
    <hogftrs_0344 trans_types="none" type="hog"/>  
    <hogftrs_0345 trans_types="none" type="hog"/>  
    <hogftrs_0346 trans_types="none" type="hog"/>  
    <hogftrs_0347 trans_types="none" type="hog"/>  
    <hogftrs_0348 trans_types="none" type="hog"/>  
    <hogftrs_0349 trans_types="none" type="hog"/>  
    <hogftrs_0350 trans_types="none" type="hog"/>  
    <hogftrs_0351 trans_types="none" type="hog"/>  
    <hogftrs_0352 trans_types="none" type="hog"/>  
    <hogftrs_0353 trans_types="none" type="hog"/>  
    <hogftrs_0354 trans_types="none" type="hog"/>  
    <hogftrs_0355 trans_types="none" type="hog"/>  
    <hogftrs_0356 trans_types="none" type="hog"/>  
    <hogftrs_0357 trans_types="none" type="hog"/>  
    <hogftrs_0358 trans_types="none" type="hog"/>  
    <hogftrs_0359 trans_types="none" type="hog"/>  
    <hogftrs_0360 trans_types="none" type="hog"/>  
    <hogftrs_0361 trans_types="none" type="hog"/>  
    <hogftrs_0362 trans_types="none" type="hog"/>  
    <hogftrs_0363 trans_types="none" type="hog"/>  
    <hogftrs_0364 trans_types="none" type="hog"/>  
    <hogftrs_0365 trans_types="none" type="hog"/>  
    <hogftrs_0366 trans_types="none" type="hog"/>  
    <hogftrs_0367 trans_types="none" type="hog"/>  
    <hogftrs_0368 trans_types="none" type="hog"/>  
    <hogftrs_0369 trans_types="none" type="hog"/>  
    <hogftrs_0370 trans_types="none" type="hog"/>  
    <hogftrs_0371 trans_types="none" type="hog"/>  
    <hogftrs_0372 trans_types="none" type="hog"/>  
    <hogftrs_0373 trans_types="none" type="hog"/>  
    <hogftrs_0374 trans_types="none" type="hog"/>  
    <hogftrs_0375 trans_types="none" type="hog"/>  
    <hogftrs_0376 trans_types="none" type="hog"/>  
    <hogftrs_0377 trans_types="none" type="hog"/>  
    <hogftrs_0378 trans_types="none" type="hog"/>  
    <hogftrs_0379 trans_types="none" type="hog"/>  
    <hogftrs_0380 trans_types="none" type="hog"/>  
    <hogftrs_0381 trans_types="none" type="hog"/>  
    <hogftrs_0382 trans_types="none" type="hog"/>  
    <hogftrs_0383 trans_types="none" type="hog"/>  
    <hogftrs_0384 trans_types="none" type="hog"/>  
    <hogftrs_0385 trans_types="none" type="hog"/>  
    <hogftrs_0386 trans_types="none" type="hog"/>  
    <hogftrs_0387 trans_types="none" type="hog"/>  
    <hogftrs_0388 trans_types="none" type="hog"/>  
    <hogftrs_0389 trans_types="none" type="hog"/>  
    <hogftrs_0390 trans_types="none" type="hog"/>  
    <hogftrs_0391 trans_types="none" type="hog"/>  
    <hogftrs_0392 trans_types="none" type="hog"/>  
    <hogftrs_0393 trans_types="none" type="hog"/>  
    <hogftrs_0394 trans_types="none" type="hog"/>  
    <hogftrs_0395 trans_types="none" type="hog"/>  
    <hogftrs_0396 trans_types="none" type="hog"/>  
    <hogftrs_0397 trans_types="none" type="hog"/>  
    <hogftrs_0398 trans_types="none" type="hog"/>  
    <hogftrs_0399 trans_types="none" type="hog"/>  
    <hogftrs_0400 trans_types="none" type="hog"/>  
    <hogftrs_0401 trans_types="none" type="hog"/>  
    <hogftrs_0402 trans_types="none" type="hog"/>  
    <hogftrs_0403 trans_types="none" type="hog"/>  
    <hogftrs_0404 trans_types="none" type="hog"/>  
    <hogftrs_0405 trans_types="none" type="hog"/>  
    <hogftrs_0406 trans_types="none" type="hog"/>  
    <hogftrs_0407 trans_types="none" type="hog"/>  
    <hogftrs_0408 trans_types="none" type="hog"/>  
    <hogftrs_0409 trans_types="none" type="hog"/>  
    <hogftrs_0410 trans_types="none" type="hog"/>  
    <hogftrs_0411 trans_types="none" type="hog"/>  
    <hogftrs_0412 trans_types="none" type="hog"/>  
    <hogftrs_0413 trans_types="none" type="hog"/>  
    <hogftrs_0414 trans_types="none" type="hog"/>  
    <hogftrs_0415 trans_types="none" type="hog"/>  
    <hogftrs_0416 trans_types="none" type="hog"/>  
    <hogftrs_0417 trans_types="none" type="hog"/>  
    <hogftrs_0418 trans_types="none" type="hog"/>  
    <hogftrs_0419 trans_types="none" type="hog"/>  
    <hogftrs_0420 trans_types="none" type="hog"/>  
    <hogftrs_0421 trans_types="none" type="hog"/>  
    <hogftrs_0422 trans_types="none" type="hog"/>  
    <hogftrs_0423 trans_types="none" type="hog"/>  
    <hogftrs_0424 trans_types="none" type="hog"/>  
    <hogftrs_0425 trans_types="none" type="hog"/>  
    <hogftrs_0426 trans_types="none" type="hog"/>  
    <hogftrs_0427 trans_types="none" type="hog"/>  
    <hogftrs_0428 trans_types="none" type="hog"/>  
    <hogftrs_0429 trans_types="none" type="hog"/>  
    <hogftrs_0430 trans_types="none" type="hog"/>  
    <hogftrs_0431 trans_types="none" type="hog"/>  
    <hogftrs_0432 trans_types="none" type="hog"/>  
    <hogftrs_0433 trans_types="none" type="hog"/>  
    <hogftrs_0434 trans_types="none" type="hog"/>  
    <hogftrs_0435 trans_types="none" type="hog"/>  
    <hogftrs_0436 trans_types="none" type="hog"/>  
    <hogftrs_0437 trans_types="none" type="hog"/>  
    <hogftrs_0438 trans_types="none" type="hog"/>  
    <hogftrs_0439 trans_types="none" type="hog"/>  
    <hogftrs_0440 trans_types="none" type="hog"/>  
    <hogftrs_0441 trans_types="none" type="hog"/>  
    <hogftrs_0442 trans_types="none" type="hog"/>  
    <hogftrs_0443 trans_types="none" type="hog"/>  
    <hogftrs_0444 trans_types="none" type="hog"/>  
    <hogftrs_0445 trans_types="none" type="hog"/>  
    <hogftrs_0446 trans_types="none" type="hog"/>  
    <hogftrs_0447 trans_types="none" type="hog"/>  
    <hogftrs_0448 trans_types="none" type="hog"/>  
    <hogftrs_0449 trans_types="none" type="hog"/>  
    <hogftrs_0450 trans_types="none" type="hog"/>  
    <hogftrs_0451 trans_types="none" type="hog"/>  
    <hogftrs_0452 trans_types="none" type="hog"/>  
    <hogftrs_0453 trans_types="none" type="hog"/>  
    <hogftrs_0454 trans_types="none" type="hog"/>  
    <hogftrs_0455 trans_types="none" type="hog"/>  
    <hogftrs_0456 trans_types="none" type="hog"/>  
    <hogftrs_0457 trans_types="none" type="hog"/>  
    <hogftrs_0458 trans_types="none" type="hog"/>  
    <hogftrs_0459 trans_types="none" type="hog"/>  
    <hogftrs_0460 trans_types="none" type="hog"/>  
    <hogftrs_0461 trans_types="none" type="hog"/>  
    <hogftrs_0462 trans_types="none" type="hog"/>  
    <hogftrs_0463 trans_types="none" type="hog"/>  
    <hogftrs_0464 trans_types="none" type="hog"/>  
    <hogftrs_0465 trans_types="none" type="hog"/>  
    <hogftrs_0466 trans_types="none" type="hog"/>  
    <hogftrs_0467 trans_types="none" type="hog"/>  
    <hogftrs_0468 trans_types="none" type="hog"/>  
    <hogftrs_0469 trans_types="none" type="hog"/>  
    <hogftrs_0470 trans_types="none" type="hog"/>  
    <hogftrs_0471 trans_types="none" type="hog"/>  
    <hogftrs_0472 trans_types="none" type="hog"/>  
    <hogftrs_0473 trans_types="none" type="hog"/>  
    <hogftrs_0474 trans_types="none" type="hog"/>  
    <hogftrs_0475 trans_types="none" type="hog"/>  
    <hogftrs_0476 trans_types="none" type="hog"/>  
    <hogftrs_0477 trans_types="none" type="hog"/>  
    <hogftrs_0478 trans_types="none" type="hog"/>  
    <hogftrs_0479 trans_types="none" type="hog"/>  
    <hogftrs_0480 trans_types="none" type="hog"/>  
    <hogftrs_0481 trans_types="none" type="hog"/>  
    <hogftrs_0482 trans_types="none" type="hog"/>  
    <hogftrs_0483 trans_types="none" type="hog"/>  
    <hogftrs_0484 trans_types="none" type="hog"/>  
    <hogftrs_0485 trans_types="none" type="hog"/>  
    <hogftrs_0486 trans_types="none" type="hog"/>  
    <hogftrs_0487 trans_types="none" type="hog"/>  
    <hogftrs_0488 trans_types="none" type="hog"/>  
    <hogftrs_0489 trans_types="none" type="hog"/>  
    <hogftrs_0490 trans_types="none" type="hog"/>  
    <hogftrs_0491 trans_types="none" type="hog"/>  
    <hogftrs_0492 trans_types="none" type="hog"/>  
    <hogftrs_0493 trans_types="none" type="hog"/>  
    <hogftrs_0494 trans_types="none" type="hog"/>  
    <hogftrs_0495 trans_types="none" type="hog"/>  
    <hogftrs_0496 trans_types="none" type="hog"/>  
    <hogftrs_0497 trans_types="none" type="hog"/>  
    <hogftrs_0498 trans_types="none" type="hog"/>  
    <hogftrs_0499 trans_types="none" type="hog"/>  
    <hogftrs_0500 trans_types="none" type="hog"/>  
    <hogftrs_0501 trans_types="none" type="hog"/>  
    <hogftrs_0502 trans_types="none" type="hog"/>  
    <hogftrs_0503 trans_types="none" type="hog"/>  
    <hogftrs_0504 trans_types="none" type="hog"/>  
    <hogftrs_0505 trans_types="none" type="hog"/>  
    <hogftrs_0506 trans_types="none" type="hog"/>  
    <hogftrs_0507 trans_types="none" type="hog"/>  
    <hogftrs_0508 trans_types="none" type="hog"/>  
    <hogftrs_0509 trans_types="none" type="hog"/>  
    <hogftrs_0510 trans_types="none" type="hog"/>  
    <hogftrs_0511 trans_types="none" type="hog"/>  
    <hogftrs_0512 trans_types="none" type="hog"/>    
   
    <flowftrs_0001 trans_types="none" type="flow"/>  
    <flowftrs_0002 trans_types="none" type="flow"/>  
    <flowftrs_0003 trans_types="none" type="flow"/>  
    <flowftrs_0004 trans_types="none" type="flow"/>  
    <flowftrs_0005 trans_types="none" type="flow"/>  
    <flowftrs_0006 trans_types="none" type="flow"/>  
    <flowftrs_0007 trans_types="none" type="flow"/>  
    <flowftrs_0008 trans_types="none" type="flow"/>  
    <flowftrs_0009 trans_types="none" type="flow"/>  
    <flowftrs_0010 trans_types="none" type="flow"/>  
    <flowftrs_0011 trans_types="none" type="flow"/>  
    <flowftrs_0012 trans_types="none" type="flow"/>  
    <flowftrs_0013 trans_types="none" type="flow"/>  
    <flowftrs_0014 trans_types="none" type="flow"/>  
    <flowftrs_0015 trans_types="none" type="flow"/>  
    <flowftrs_0016 trans_types="none" type="flow"/>  
    <flowftrs_0017 trans_types="none" type="flow"/>  
    <flowftrs_0018 trans_types="none" type="flow"/>  
    <flowftrs_0019 trans_types="none" type="flow"/>  
    <flowftrs_0020 trans_types="none" type="flow"/>  
    <flowftrs_0021 trans_types="none" type="flow"/>  
    <flowftrs_0022 trans_types="none" type="flow"/>  
    <flowftrs_0023 trans_types="none" type="flow"/>  
    <flowftrs_0024 trans_types="none" type="flow"/>  
    <flowftrs_0025 trans_types="none" type="flow"/>  
    <flowftrs_0026 trans_types="none" type="flow"/>  
    <flowftrs_0027 trans_types="none" type="flow"/>  
    <flowftrs_0028 trans_types="none" type="flow"/>  
    <flowftrs_0029 trans_types="none" type="flow"/>  
    <flowftrs_0030 trans_types="none" type="flow"/>  
    <flowftrs_0031 trans_types="none" type="flow"/>  
    <flowftrs_0032 trans_types="none" type="flow"/>  
    <flowftrs_0033 trans_types="none" type="flow"/>  
    <flowftrs_0034 trans_types="none" type="flow"/>  
    <flowftrs_0035 trans_types="none" type="flow"/>  
    <flowftrs_0036 trans_types="none" type="flow"/>  
    <flowftrs_0037 trans_types="none" type="flow"/>  
    <flowftrs_0038 trans_types="none" type="flow"/>  
    <flowftrs_0039 trans_types="none" type="flow"/>  
    <flowftrs_0040 trans_types="none" type="flow"/>  
    <flowftrs_0041 trans_types="none" type="flow"/>  
    <flowftrs_0042 trans_types="none" type="flow"/>  
    <flowftrs_0043 trans_types="none" type="flow"/>  
    <flowftrs_0044 trans_types="none" type="flow"/>  
    <flowftrs_0045 trans_types="none" type="flow"/>  
    <flowftrs_0046 trans_types="none" type="flow"/>  
    <flowftrs_0047 trans_types="none" type="flow"/>  
    <flowftrs_0048 trans_types="none" type="flow"/>  
    <flowftrs_0049 trans_types="none" type="flow"/>  
    <flowftrs_0050 trans_types="none" type="flow"/>  
    <flowftrs_0051 trans_types="none" type="flow"/>  
    <flowftrs_0052 trans_types="none" type="flow"/>  
    <flowftrs_0053 trans_types="none" type="flow"/>  
    <flowftrs_0054 trans_types="none" type="flow"/>  
    <flowftrs_0055 trans_types="none" type="flow"/>  
    <flowftrs_0056 trans_types="none" type="flow"/>  
    <flowftrs_0057 trans_types="none" type="flow"/>  
    <flowftrs_0058 trans_types="none" type="flow"/>  
    <flowftrs_0059 trans_types="none" type="flow"/>  
    <flowftrs_0060 trans_types="none" type="flow"/>  
    <flowftrs_0061 trans_types="none" type="flow"/>  
    <flowftrs_0062 trans_types="none" type="flow"/>  
    <flowftrs_0063 trans_types="none" type="flow"/>  
    <flowftrs_0064 trans_types="none" type="flow"/>  
    <flowftrs_0065 trans_types="none" type="flow"/>  
    <flowftrs_0066 trans_types="none" type="flow"/>  
    <flowftrs_0067 trans_types="none" type="flow"/>  
    <flowftrs_0068 trans_types="none" type="flow"/>  
    <flowftrs_0069 trans_types="none" type="flow"/>  
    <flowftrs_0070 trans_types="none" type="flow"/>  
    <flowftrs_0071 trans_types="none" type="flow"/>  
    <flowftrs_0072 trans_types="none" type="flow"/>  
    <flowftrs_0073 trans_types="none" type="flow"/>  
    <flowftrs_0074 trans_types="none" type="flow"/>  
    <flowftrs_0075 trans_types="none" type="flow"/>  
    <flowftrs_0076 trans_types="none" type="flow"/>  
    <flowftrs_0077 trans_types="none" type="flow"/>  
    <flowftrs_0078 trans_types="none" type="flow"/>  
    <flowftrs_0079 trans_types="none" type="flow"/>  
    <flowftrs_0080 trans_types="none" type="flow"/>  
    <flowftrs_0081 trans_types="none" type="flow"/>  
    <flowftrs_0082 trans_types="none" type="flow"/>  
    <flowftrs_0083 trans_types="none" type="flow"/>  
    <flowftrs_0084 trans_types="none" type="flow"/>  
    <flowftrs_0085 trans_types="none" type="flow"/>  
    <flowftrs_0086 trans_types="none" type="flow"/>  
    <flowftrs_0087 trans_types="none" type="flow"/>  
    <flowftrs_0088 trans_types="none" type="flow"/>  
    <flowftrs_0089 trans_types="none" type="flow"/>  
    <flowftrs_0090 trans_types="none" type="flow"/>  
    <flowftrs_0091 trans_types="none" type="flow"/>  
    <flowftrs_0092 trans_types="none" type="flow"/>  
    <flowftrs_0093 trans_types="none" type="flow"/>  
    <flowftrs_0094 trans_types="none" type="flow"/>  
    <flowftrs_0095 trans_types="none" type="flow"/>  
    <flowftrs_0096 trans_types="none" type="flow"/>  
    <flowftrs_0097 trans_types="none" type="flow"/>  
    <flowftrs_0098 trans_types="none" type="flow"/>  
    <flowftrs_0099 trans_types="none" type="flow"/>  
    <flowftrs_0100 trans_types="none" type="flow"/>  
    <flowftrs_0101 trans_types="none" type="flow"/>  
    <flowftrs_0102 trans_types="none" type="flow"/>  
    <flowftrs_0103 trans_types="none" type="flow"/>  
    <flowftrs_0104 trans_types="none" type="flow"/>  
    <flowftrs_0105 trans_types="none" type="flow"/>  
    <flowftrs_0106 trans_types="none" type="flow"/>  
    <flowftrs_0107 trans_types="none" type="flow"/>  
    <flowftrs_0108 trans_types="none" type="flow"/>  
    <flowftrs_0109 trans_types="none" type="flow"/>  
    <flowftrs_0110 trans_types="none" type="flow"/>  
    <flowftrs_0111 trans_types="none" type="flow"/>  
    <flowftrs_0112 trans_types="none" type="flow"/>  
    <flowftrs_0113 trans_types="none" type="flow"/>  
    <flowftrs_0114 trans_types="none" type="flow"/>  
    <flowftrs_0115 trans_types="none" type="flow"/>  
    <flowftrs_0116 trans_types="none" type="flow"/>  
    <flowftrs_0117 trans_types="none" type="flow"/>  
    <flowftrs_0118 trans_types="none" type="flow"/>  
    <flowftrs_0119 trans_types="none" type="flow"/>  
    <flowftrs_0120 trans_types="none" type="flow"/>  
    <flowftrs_0121 trans_types="none" type="flow"/>  
    <flowftrs_0122 trans_types="none" type="flow"/>  
    <flowftrs_0123 trans_types="none" type="flow"/>  
    <flowftrs_0124 trans_types="none" type="flow"/>  
    <flowftrs_0125 trans_types="none" type="flow"/>  
    <flowftrs_0126 trans_types="none" type="flow"/>  
    <flowftrs_0127 trans_types="none" type="flow"/>  
    <flowftrs_0128 trans_types="none" type="flow"/>  
    <flowftrs_0129 trans_types="none" type="flow"/>  
    <flowftrs_0130 trans_types="none" type="flow"/>  
    <flowftrs_0131 trans_types="none" type="flow"/>  
    <flowftrs_0132 trans_types="none" type="flow"/>  
    <flowftrs_0133 trans_types="none" type="flow"/>  
    <flowftrs_0134 trans_types="none" type="flow"/>  
    <flowftrs_0135 trans_types="none" type="flow"/>  
    <flowftrs_0136 trans_types="none" type="flow"/>  
    <flowftrs_0137 trans_types="none" type="flow"/>  
    <flowftrs_0138 trans_types="none" type="flow"/>  
    <flowftrs_0139 trans_types="none" type="flow"/>  
    <flowftrs_0140 trans_types="none" type="flow"/>  
    <flowftrs_0141 trans_types="none" type="flow"/>  
    <flowftrs_0142 trans_types="none" type="flow"/>  
    <flowftrs_0143 trans_types="none" type="flow"/>  
    <flowftrs_0144 trans_types="none" type="flow"/>  
    <flowftrs_0145 trans_types="none" type="flow"/>  
    <flowftrs_0146 trans_types="none" type="flow"/>  
    <flowftrs_0147 trans_types="none" type="flow"/>  
    <flowftrs_0148 trans_types="none" type="flow"/>  
    <flowftrs_0149 trans_types="none" type="flow"/>  
    <flowftrs_0150 trans_types="none" type="flow"/>  
    <flowftrs_0151 trans_types="none" type="flow"/>  
    <flowftrs_0152 trans_types="none" type="flow"/>  
    <flowftrs_0153 trans_types="none" type="flow"/>  
    <flowftrs_0154 trans_types="none" type="flow"/>  
    <flowftrs_0155 trans_types="none" type="flow"/>  
    <flowftrs_0156 trans_types="none" type="flow"/>  
    <flowftrs_0157 trans_types="none" type="flow"/>  
    <flowftrs_0158 trans_types="none" type="flow"/>  
    <flowftrs_0159 trans_types="none" type="flow"/>  
    <flowftrs_0160 trans_types="none" type="flow"/>  
    <flowftrs_0161 trans_types="none" type="flow"/>  
    <flowftrs_0162 trans_types="none" type="flow"/>  
    <flowftrs_0163 trans_types="none" type="flow"/>  
    <flowftrs_0164 trans_types="none" type="flow"/>  
    <flowftrs_0165 trans_types="none" type="flow"/>  
    <flowftrs_0166 trans_types="none" type="flow"/>  
    <flowftrs_0167 trans_types="none" type="flow"/>  
    <flowftrs_0168 trans_types="none" type="flow"/>  
    <flowftrs_0169 trans_types="none" type="flow"/>  
    <flowftrs_0170 trans_types="none" type="flow"/>  
    <flowftrs_0171 trans_types="none" type="flow"/>  
    <flowftrs_0172 trans_types="none" type="flow"/>  
    <flowftrs_0173 trans_types="none" type="flow"/>  
    <flowftrs_0174 trans_types="none" type="flow"/>  
    <flowftrs_0175 trans_types="none" type="flow"/>  
    <flowftrs_0176 trans_types="none" type="flow"/>  
    <flowftrs_0177 trans_types="none" type="flow"/>  
    <flowftrs_0178 trans_types="none" type="flow"/>  
    <flowftrs_0179 trans_types="none" type="flow"/>  
    <flowftrs_0180 trans_types="none" type="flow"/>  
    <flowftrs_0181 trans_types="none" type="flow"/>  
    <flowftrs_0182 trans_types="none" type="flow"/>  
    <flowftrs_0183 trans_types="none" type="flow"/>  
    <flowftrs_0184 trans_types="none" type="flow"/>  
    <flowftrs_0185 trans_types="none" type="flow"/>  
    <flowftrs_0186 trans_types="none" type="flow"/>  
    <flowftrs_0187 trans_types="none" type="flow"/>  
    <flowftrs_0188 trans_types="none" type="flow"/>  
    <flowftrs_0189 trans_types="none" type="flow"/>  
    <flowftrs_0190 trans_types="none" type="flow"/>  
    <flowftrs_0191 trans_types="none" type="flow"/>  
    <flowftrs_0192 trans_types="none" type="flow"/>  
    <flowftrs_0193 trans_types="none" type="flow"/>  
    <flowftrs_0194 trans_types="none" type="flow"/>  
    <flowftrs_0195 trans_types="none" type="flow"/>  
    <flowftrs_0196 trans_types="none" type="flow"/>  
    <flowftrs_0197 trans_types="none" type="flow"/>  
    <flowftrs_0198 trans_types="none" type="flow"/>  
    <flowftrs_0199 trans_types="none" type="flow"/>  
    <flowftrs_0200 trans_types="none" type="flow"/>  
    <flowftrs_0201 trans_types="none" type="flow"/>  
    <flowftrs_0202 trans_types="none" type="flow"/>  
    <flowftrs_0203 trans_types="none" type="flow"/>  
    <flowftrs_0204 trans_types="none" type="flow"/>  
    <flowftrs_0205 trans_types="none" type="flow"/>  
    <flowftrs_0206 trans_types="none" type="flow"/>  
    <flowftrs_0207 trans_types="none" type="flow"/>  
    <flowftrs_0208 trans_types="none" type="flow"/>  
    <flowftrs_0209 trans_types="none" type="flow"/>  
    <flowftrs_0210 trans_types="none" type="flow"/>  
    <flowftrs_0211 trans_types="none" type="flow"/>  
    <flowftrs_0212 trans_types="none" type="flow"/>  
    <flowftrs_0213 trans_types="none" type="flow"/>  
    <flowftrs_0214 trans_types="none" type="flow"/>  
    <flowftrs_0215 trans_types="none" type="flow"/>  
    <flowftrs_0216 trans_types="none" type="flow"/>  
    <flowftrs_0217 trans_types="none" type="flow"/>  
    <flowftrs_0218 trans_types="none" type="flow"/>  
    <flowftrs_0219 trans_types="none" type="flow"/>  
    <flowftrs_0220 trans_types="none" type="flow"/>  
    <flowftrs_0221 trans_types="none" type="flow"/>  
    <flowftrs_0222 trans_types="none" type="flow"/>  
    <flowftrs_0223 trans_types="none" type="flow"/>  
    <flowftrs_0224 trans_types="none" type="flow"/>  
    <flowftrs_0225 trans_types="none" type="flow"/>  
    <flowftrs_0226 trans_types="none" type="flow"/>  
    <flowftrs_0227 trans_types="none" type="flow"/>  
    <flowftrs_0228 trans_types="none" type="flow"/>  
    <flowftrs_0229 trans_types="none" type="flow"/>  
    <flowftrs_0230 trans_types="none" type="flow"/>  
    <flowftrs_0231 trans_types="none" type="flow"/>  
    <flowftrs_0232 trans_types="none" type="flow"/>  
    <flowftrs_0233 trans_types="none" type="flow"/>  
    <flowftrs_0234 trans_types="none" type="flow"/>  
    <flowftrs_0235 trans_types="none" type="flow"/>  
    <flowftrs_0236 trans_types="none" type="flow"/>  
    <flowftrs_0237 trans_types="none" type="flow"/>  
    <flowftrs_0238 trans_types="none" type="flow"/>  
    <flowftrs_0239 trans_types="none" type="flow"/>  
    <flowftrs_0240 trans_types="none" type="flow"/>  
    <flowftrs_0241 trans_types="none" type="flow"/>  
    <flowftrs_0242 trans_types="none" type="flow"/>  
    <flowftrs_0243 trans_types="none" type="flow"/>  
    <flowftrs_0244 trans_types="none" type="flow"/>  
    <flowftrs_0245 trans_types="none" type="flow"/>  
    <flowftrs_0246 trans_types="none" type="flow"/>  
    <flowftrs_0247 trans_types="none" type="flow"/>  
    <flowftrs_0248 trans_types="none" type="flow"/>  
    <flowftrs_0249 trans_types="none" type="flow"/>  
    <flowftrs_0250 trans_types="none" type="flow"/>  
    <flowftrs_0251 trans_types="none" type="flow"/>  
    <flowftrs_0252 trans_types="none" type="flow"/>  
    <flowftrs_0253 trans_types="none" type="flow"/>  
    <flowftrs_0254 trans_types="none" type="flow"/>  
    <flowftrs_0255 trans_types="none" type="flow"/>  
    <flowftrs_0256 trans_types="none" type="flow"/>  
    <flowftrs_0257 trans_types="none" type="flow"/>  
    <flowftrs_0258 trans_types="none" type="flow"/>  
    <flowftrs_0259 trans_types="none" type="flow"/>  
    <flowftrs_0260 trans_types="none" type="flow"/>  
    <flowftrs_0261 trans_types="none" type="flow"/>  
    <flowftrs_0262 trans_types="none" type="flow"/>  
    <flowftrs_0263 trans_types="none" type="flow"/>  
    <flowftrs_0264 trans_types="none" type="flow"/>  
    <flowftrs_0265 trans_types="none" type="flow"/>  
    <flowftrs_0266 trans_types="none" type="flow"/>  
    <flowftrs_0267 trans_types="none" type="flow"/>  
    <flowftrs_0268 trans_types="none" type="flow"/>  
    <flowftrs_0269 trans_types="none" type="flow"/>  
    <flowftrs_0270 trans_types="none" type="flow"/>  
    <flowftrs_0271 trans_types="none" type="flow"/>  
    <flowftrs_0272 trans_types="none" type="flow"/>  
    <flowftrs_0273 trans_types="none" type="flow"/>  
    <flowftrs_0274 trans_types="none" type="flow"/>  
    <flowftrs_0275 trans_types="none" type="flow"/>  
    <flowftrs_0276 trans_types="none" type="flow"/>  
    <flowftrs_0277 trans_types="none" type="flow"/>  
    <flowftrs_0278 trans_types="none" type="flow"/>  
    <flowftrs_0279 trans_types="none" type="flow"/>  
    <flowftrs_0280 trans_types="none" type="flow"/>  
    <flowftrs_0281 trans_types="none" type="flow"/>  
    <flowftrs_0282 trans_types="none" type="flow"/>  
    <flowftrs_0283 trans_types="none" type="flow"/>  
    <flowftrs_0284 trans_types="none" type="flow"/>  
    <flowftrs_0285 trans_types="none" type="flow"/>  
    <flowftrs_0286 trans_types="none" type="flow"/>  
    <flowftrs_0287 trans_types="none" type="flow"/>  
    <flowftrs_0288 trans_types="none" type="flow"/>  
    <flowftrs_0289 trans_types="none" type="flow"/>  
    <flowftrs_0290 trans_types="none" type="flow"/>  
    <flowftrs_0291 trans_types="none" type="flow"/>  
    <flowftrs_0292 trans_types="none" type="flow"/>  
    <flowftrs_0293 trans_types="none" type="flow"/>  
    <flowftrs_0294 trans_types="none" type="flow"/>  
    <flowftrs_0295 trans_types="none" type="flow"/>  
    <flowftrs_0296 trans_types="none" type="flow"/>  
    <flowftrs_0297 trans_types="none" type="flow"/>  
    <flowftrs_0298 trans_types="none" type="flow"/>  
    <flowftrs_0299 trans_types="none" type="flow"/>  
    <flowftrs_0300 trans_types="none" type="flow"/>  
    <flowftrs_0301 trans_types="none" type="flow"/>  
    <flowftrs_0302 trans_types="none" type="flow"/>  
    <flowftrs_0303 trans_types="none" type="flow"/>  
    <flowftrs_0304 trans_types="none" type="flow"/>  
    <flowftrs_0305 trans_types="none" type="flow"/>  
    <flowftrs_0306 trans_types="none" type="flow"/>  
    <flowftrs_0307 trans_types="none" type="flow"/>  
    <flowftrs_0308 trans_types="none" type="flow"/>  
    <flowftrs_0309 trans_types="none" type="flow"/>  
    <flowftrs_0310 trans_types="none" type="flow"/>  
    <flowftrs_0311 trans_types="none" type="flow"/>  
    <flowftrs_0312 trans_types="none" type="flow"/>  
    <flowftrs_0313 trans_types="none" type="flow"/>  
    <flowftrs_0314 trans_types="none" type="flow"/>  
    <flowftrs_0315 trans_types="none" type="flow"/>  
    <flowftrs_0316 trans_types="none" type="flow"/>  
    <flowftrs_0317 trans_types="none" type="flow"/>  
    <flowftrs_0318 trans_types="none" type="flow"/>  
    <flowftrs_0319 trans_types="none" type="flow"/>  
    <flowftrs_0320 trans_types="none" type="flow"/>  
    <flowftrs_0321 trans_types="none" type="flow"/>  
    <flowftrs_0322 trans_types="none" type="flow"/>  
    <flowftrs_0323 trans_types="none" type="flow"/>  
    <flowftrs_0324 trans_types="none" type="flow"/>  
    <flowftrs_0325 trans_types="none" type="flow"/>  
    <flowftrs_0326 trans_types="none" type="flow"/>  
    <flowftrs_0327 trans_types="none" type="flow"/>  
    <flowftrs_0328 trans_types="none" type="flow"/>  
    <flowftrs_0329 trans_types="none" type="flow"/>  
    <flowftrs_0330 trans_types="none" type="flow"/>  
    <flowftrs_0331 trans_types="none" type="flow"/>  
    <flowftrs_0332 trans_types="none" type="flow"/>  
    <flowftrs_0333 trans_types="none" type="flow"/>  
    <flowftrs_0334 trans_types="none" type="flow"/>  
    <flowftrs_0335 trans_types="none" type="flow"/>  
    <flowftrs_0336 trans_types="none" type="flow"/>  
    <flowftrs_0337 trans_types="none" type="flow"/>  
    <flowftrs_0338 trans_types="none" type="flow"/>  
    <flowftrs_0339 trans_types="none" type="flow"/>  
    <flowftrs_0340 trans_types="none" type="flow"/>  
    <flowftrs_0341 trans_types="none" type="flow"/>  
    <flowftrs_0342 trans_types="none" type="flow"/>  
    <flowftrs_0343 trans_types="none" type="flow"/>  
    <flowftrs_0344 trans_types="none" type="flow"/>  
    <flowftrs_0345 trans_types="none" type="flow"/>  
    <flowftrs_0346 trans_types="none" type="flow"/>  
    <flowftrs_0347 trans_types="none" type="flow"/>  
    <flowftrs_0348 trans_types="none" type="flow"/>  
    <flowftrs_0349 trans_types="none" type="flow"/>  
    <flowftrs_0350 trans_types="none" type="flow"/>  
    <flowftrs_0351 trans_types="none" type="flow"/>  
    <flowftrs_0352 trans_types="none" type="flow"/>  
    <flowftrs_0353 trans_types="none" type="flow"/>  
    <flowftrs_0354 trans_types="none" type="flow"/>  
    <flowftrs_0355 trans_types="none" type="flow"/>  
    <flowftrs_0356 trans_types="none" type="flow"/>  
    <flowftrs_0357 trans_types="none" type="flow"/>  
    <flowftrs_0358 trans_types="none" type="flow"/>  
    <flowftrs_0359 trans_types="none" type="flow"/>  
    <flowftrs_0360 trans_types="none" type="flow"/>  
    <flowftrs_0361 trans_types="none" type="flow"/>  
    <flowftrs_0362 trans_types="none" type="flow"/>  
    <flowftrs_0363 trans_types="none" type="flow"/>  
    <flowftrs_0364 trans_types="none" type="flow"/>  
    <flowftrs_0365 trans_types="none" type="flow"/>  
    <flowftrs_0366 trans_types="none" type="flow"/>  
    <flowftrs_0367 trans_types="none" type="flow"/>  
    <flowftrs_0368 trans_types="none" type="flow"/>  
    <flowftrs_0369 trans_types="none" type="flow"/>  
    <flowftrs_0370 trans_types="none" type="flow"/>  
    <flowftrs_0371 trans_types="none" type="flow"/>  
    <flowftrs_0372 trans_types="none" type="flow"/>  
    <flowftrs_0373 trans_types="none" type="flow"/>  
    <flowftrs_0374 trans_types="none" type="flow"/>  
    <flowftrs_0375 trans_types="none" type="flow"/>  
    <flowftrs_0376 trans_types="none" type="flow"/>  
    <flowftrs_0377 trans_types="none" type="flow"/>  
    <flowftrs_0378 trans_types="none" type="flow"/>  
    <flowftrs_0379 trans_types="none" type="flow"/>  
    <flowftrs_0380 trans_types="none" type="flow"/>  
    <flowftrs_0381 trans_types="none" type="flow"/>  
    <flowftrs_0382 trans_types="none" type="flow"/>  
    <flowftrs_0383 trans_types="none" type="flow"/>  
    <flowftrs_0384 trans_types="none" type="flow"/>  
    <flowftrs_0385 trans_types="none" type="flow"/>  
    <flowftrs_0386 trans_types="none" type="flow"/>  
    <flowftrs_0387 trans_types="none" type="flow"/>  
    <flowftrs_0388 trans_types="none" type="flow"/>  
    <flowftrs_0389 trans_types="none" type="flow"/>  
    <flowftrs_0390 trans_types="none" type="flow"/>  
    <flowftrs_0391 trans_types="none" type="flow"/>  
    <flowftrs_0392 trans_types="none" type="flow"/>  
    <flowftrs_0393 trans_types="none" type="flow"/>  
    <flowftrs_0394 trans_types="none" type="flow"/>  
    <flowftrs_0395 trans_types="none" type="flow"/>  
    <flowftrs_0396 trans_types="none" type="flow"/>  
    <flowftrs_0397 trans_types="none" type="flow"/>  
    <flowftrs_0398 trans_types="none" type="flow"/>  
    <flowftrs_0399 trans_types="none" type="flow"/>  
    <flowftrs_0400 trans_types="none" type="flow"/>  
    <flowftrs_0401 trans_types="none" type="flow"/>  
    <flowftrs_0402 trans_types="none" type="flow"/>  
    <flowftrs_0403 trans_types="none" type="flow"/>  
    <flowftrs_0404 trans_types="none" type="flow"/>  
    <flowftrs_0405 trans_types="none" type="flow"/>  
    <flowftrs_0406 trans_types="none" type="flow"/>  
    <flowftrs_0407 trans_types="none" type="flow"/>  
    <flowftrs_0408 trans_types="none" type="flow"/>  
    <flowftrs_0409 trans_types="none" type="flow"/>  
    <flowftrs_0410 trans_types="none" type="flow"/>  
    <flowftrs_0411 trans_types="none" type="flow"/>  
    <flowftrs_0412 trans_types="none" type="flow"/>  
    <flowftrs_0413 trans_types="none" type="flow"/>  
    <flowftrs_0414 trans_types="none" type="flow"/>  
    <flowftrs_0415 trans_types="none" type="flow"/>  
    <flowftrs_0416 trans_types="none" type="flow"/>  
    <flowftrs_0417 trans_types="none" type="flow"/>  
    <flowftrs_0418 trans_types="none" type="flow"/>  
    <flowftrs_0419 trans_types="none" type="flow"/>  
    <flowftrs_0420 trans_types="none" type="flow"/>  
    <flowftrs_0421 trans_types="none" type="flow"/>  
    <flowftrs_0422 trans_types="none" type="flow"/>  
    <flowftrs_0423 trans_types="none" type="flow"/>  
    <flowftrs_0424 trans_types="none" type="flow"/>  
    <flowftrs_0425 trans_types="none" type="flow"/>  
    <flowftrs_0426 trans_types="none" type="flow"/>  
    <flowftrs_0427 trans_types="none" type="flow"/>  
    <flowftrs_0428 trans_types="none" type="flow"/>  
    <flowftrs_0429 trans_types="none" type="flow"/>  
    <flowftrs_0430 trans_types="none" type="flow"/>  
    <flowftrs_0431 trans_types="none" type="flow"/>  
    <flowftrs_0432 trans_types="none" type="flow"/>  
    <flowftrs_0433 trans_types="none" type="flow"/>  
    <flowftrs_0434 trans_types="none" type="flow"/>  
    <flowftrs_0435 trans_types="none" type="flow"/>  
    <flowftrs_0436 trans_types="none" type="flow"/>  
    <flowftrs_0437 trans_types="none" type="flow"/>  
    <flowftrs_0438 trans_types="none" type="flow"/>  
    <flowftrs_0439 trans_types="none" type="flow"/>  
    <flowftrs_0440 trans_types="none" type="flow"/>  
    <flowftrs_0441 trans_types="none" type="flow"/>  
    <flowftrs_0442 trans_types="none" type="flow"/>  
    <flowftrs_0443 trans_types="none" type="flow"/>  
    <flowftrs_0444 trans_types="none" type="flow"/>  
    <flowftrs_0445 trans_types="none" type="flow"/>  
    <flowftrs_0446 trans_types="none" type="flow"/>  
    <flowftrs_0447 trans_types="none" type="flow"/>  
    <flowftrs_0448 trans_types="none" type="flow"/>  
    <flowftrs_0449 trans_types="none" type="flow"/>  
    <flowftrs_0450 trans_types="none" type="flow"/>  
    <flowftrs_0451 trans_types="none" type="flow"/>  
    <flowftrs_0452 trans_types="none" type="flow"/>  
    <flowftrs_0453 trans_types="none" type="flow"/>  
    <flowftrs_0454 trans_types="none" type="flow"/>  
    <flowftrs_0455 trans_types="none" type="flow"/>  
    <flowftrs_0456 trans_types="none" type="flow"/>  
    <flowftrs_0457 trans_types="none" type="flow"/>  
    <flowftrs_0458 trans_types="none" type="flow"/>  
    <flowftrs_0459 trans_types="none" type="flow"/>  
    <flowftrs_0460 trans_types="none" type="flow"/>  
    <flowftrs_0461 trans_types="none" type="flow"/>  
    <flowftrs_0462 trans_types="none" type="flow"/>  
    <flowftrs_0463 trans_types="none" type="flow"/>  
    <flowftrs_0464 trans_types="none" type="flow"/>  
    <flowftrs_0465 trans_types="none" type="flow"/>  
    <flowftrs_0466 trans_types="none" type="flow"/>  
    <flowftrs_0467 trans_types="none" type="flow"/>  
    <flowftrs_0468 trans_types="none" type="flow"/>  
    <flowftrs_0469 trans_types="none" type="flow"/>  
    <flowftrs_0470 trans_types="none" type="flow"/>  
    <flowftrs_0471 trans_types="none" type="flow"/>  
    <flowftrs_0472 trans_types="none" type="flow"/>  
    <flowftrs_0473 trans_types="none" type="flow"/>  
    <flowftrs_0474 trans_types="none" type="flow"/>  
    <flowftrs_0475 trans_types="none" type="flow"/>  
    <flowftrs_0476 trans_types="none" type="flow"/>  
    <flowftrs_0477 trans_types="none" type="flow"/>  
    <flowftrs_0478 trans_types="none" type="flow"/>  
    <flowftrs_0479 trans_types="none" type="flow"/>  
    <flowftrs_0480 trans_types="none" type="flow"/>  
    <flowftrs_0481 trans_types="none" type="flow"/>  
    <flowftrs_0482 trans_types="none" type="flow"/>  
    <flowftrs_0483 trans_types="none" type="flow"/>  
    <flowftrs_0484 trans_types="none" type="flow"/>  
    <flowftrs_0485 trans_types="none" type="flow"/>  
    <flowftrs_0486 trans_types="none" type="flow"/>  
    <flowftrs_0487 trans_types="none" type="flow"/>  
    <flowftrs_0488 trans_types="none" type="flow"/>  
    <flowftrs_0489 trans_types="none" type="flow"/>  
    <flowftrs_0490 trans_types="none" type="flow"/>  
    <flowftrs_0491 trans_types="none" type="flow"/>  
    <flowftrs_0492 trans_types="none" type="flow"/>  
    <flowftrs_0493 trans_types="none" type="flow"/>  
    <flowftrs_0494 trans_types="none" type="flow"/>  
    <flowftrs_0495 trans_types="none" type="flow"/>  
    <flowftrs_0496 trans_types="none" type="flow"/>  
    <flowftrs_0497 trans_types="none" type="flow"/>  
    <flowftrs_0498 trans_types="none" type="flow"/>  
    <flowftrs_0499 trans_types="none" type="flow"/>  
    <flowftrs_0500 trans_types="none" type="flow"/>  
    <flowftrs_0501 trans_types="none" type="flow"/>  
    <flowftrs_0502 trans_types="none" type="flow"/>  
    <flowftrs_0503 trans_types="none" type="flow"/>  
    <flowftrs_0504 trans_types="none" type="flow"/>  
    <flowftrs_0505 trans_types="none" type="flow"/>  
    <flowftrs_0506 trans_types="none" type="flow"/>  
    <flowftrs_0507 trans_types="none" type="flow"/>  
    <flowftrs_0508 trans_types="none" type="flow"/>  
    <flowftrs_0509 trans_types="none" type="flow"/>  
    <flowftrs_0510 trans_types="none" type="flow"/>  
    <flowftrs_0511 trans_types="none" type="flow"/>  
    <flowftrs_0512 trans_types="none" type="flow"/>    
   
  </perframe>   
     
  <perframe_params  fov="3.1416" max_dnose2ell_anglerange="127" nbodylengths_near="2.5" thetafil="0.0625,0.25,0.375,0.25,0.0625"/>   
</params>   
   
   
